{
    "Четная неделя": {
        "Понедельник": {
            "I\n8:30-10:05": null,
            "II\n10:20-11:55": null,
            "III\n12:10-13:45": null,
            "IV\n14:15-15:50": null,
            "V\n16:05-17:40": null
        },
        "Вторник": {
            "I\n8:30-10:05": "ЭКОНОМИКА упр. УАК1-4.44 Ушакова",
            "II\n10:20-11:55": "ЭКОНОМИКА лекц. УАК1-4.46 Квашина",
            "III\n12:10-13:45": "М-ДЫ ПРИНЯТ. РЕШ-Й В ПРОГР. ИНЖЕНЕР. лекц. УАК3-3.05 Никитенко",
            "IV\n14:15-15:50": null,
            "V\n16:05-17:40": null
        },
        "Среда": {
            "I\n8:30-10:05": null,
            "II\n10:20-11:55": "БЕСПРОВ. ТЕХНОЛ. ПЕРЕДАЧИ ДАННЫХ лекц. УАК3-1.57 Ткаченко",
            "III\n12:10-13:45": "ПРОЕКТИР. ПРОГРАМ. ОБЕСПЕЧЕНИЯ лекц. УАК1-4.59 Красавин",
            "IV\n14:15-15:50": "НИР  к.3",
            "V\n16:05-17:40": null
        },
        "Четверг": {
            "I\n8:30-10:05": null,
            "II\n10:20-11:55": "ТЕХНОЛ. ОБР-КИ БОЛ. ДАННЫХ лекц. УАК3-3.05 Белов",
            "III\n12:10-13:45": "ЦОС лекц. УАК3-3.05 Гагарин",
            "IV\n14:15-15:50": "КОМПЬЮТЕРНЫЕ СЕТИ И ИНТЕРНЕТ-ТЕХНОЛОГИИ к.пр. к.3"
        },
        "Пятница": {
            "I\n8:30-10:05": "ЦОС лаб. I УАК2-3.03 Гусев",
            "II\n10:20-11:55": "ПРОЕКТИР. ПРОГРАМ. ОБЕСПЕЧЕНИЯ лаб. II УАК3-3.04 Голубев I УАК3-3.03 Голубева",
            "III\n12:10-13:45": "МЕТОДЫ ПРИНЯТИЯ РЕШЕНИЙ В ПРОГРАММНОЙ ИНЖЕНЕРИИ лаб. II УАК2-3.64 Никитенко",
            "IV\n14:15-15:50": null,
            "V\n16:05-17:40": null
        },
        "Суббота": {
            "I\n8:30-10:05": "МЕТОДЫ МАШИННОГО ОБУЧЕНИЯ упр. УАК3-3.08 Кручинин",
            "II\n10:20-11:55": "МЕТОДЫ МАШИННОГО ОБУЧЕНИЯ лекц. УАК3-3.56 Кручинин",
            "III\n12:10-13:45": null
        }
    },
    "Нечетная неделя": {
        "Понедельник": {
            "I\n8:30-10:05": null,
            "II\n10:20-11:55": null,
            "III\n12:10-13:45": null,
            "IV\n14:15-15:50": null,
            "V\n16:05-17:40": null
        },
        "Вторник": {
            "I\n8:30-10:05": "М-ДЫ ПРИНЯТ. РЕШ-Й В ПРОГР. ИНЖЕНЕР. лаб. I УАК2-3.69 Никитенко",
            "II\n10:20-11:55": "ЭКОНОМИКА лекц. УАК1-4.46 Квашина",
            "III\n12:10-13:45": "М-ДЫ ПРИНЯТ. РЕШ-Й В ПРОГР. ИНЖЕНЕР. лекц. УАК3-3.05 Никитенко",
            "IV\n14:15-15:50": null,
            "V\n16:05-17:40": null
        },
        "Среда": {
            "I\n8:30-10:05": null,
            "II\n10:20-11:55": "БЕСПРОВ. ТЕХНОЛ. ПЕРЕДАЧИ ДАННЫХ лекц. УАК3-1.57 Ткаченко",
            "III\n12:10-13:45": "ПРОЕКТИР. ПРОГРАМ. ОБЕСПЕЧЕНИЯ лекц. УАК1-4.59 Красавин",
            "IV\n14:15-15:50": "НИР  к.3",
            "V\n16:05-17:40": null
        },
        "Четверг": {
            "I\n8:30-10:05": null,
            "II\n10:20-11:55": "ТЕХНОЛ. ОБР-КИ БОЛ. ДАННЫХ лекц. УАК3-3.05 Белов",
            "III\n12:10-13:45": "ЦОС лекц. УАК3-3.05 Гагарин",
            "IV\n14:15-15:50": "КОМПЬЮТЕРНЫЕ СЕТИ И ИНТЕРНЕТ-ТЕХНОЛОГИИ к.пр. к.3"
        },
        "Пятница": {
            "I\n8:30-10:05": "ЦОС лаб. II УАК2-3.03 Гусев",
            "II\n10:20-11:55": "ПРОЕКТИР. ПРОГРАМ. ОБЕСПЕЧЕНИЯ лаб. II УАК3-3.04 Голубев I УАК3-3.03 Голубева",
            "III\n12:10-13:45": "БЕСПРОВ. ТЕХНОЛ. ПЕРЕДАЧИ ДАННЫХ упр. УАК2-2.07 Ткаченко",
            "IV\n14:15-15:50": null,
            "V\n16:05-17:40": null
        },
        "Суббота": {
            "I\n8:30-10:05": "ТЕХНОЛ. ОБР-КИ БОЛ. ДАННЫХ лаб. II УАК2-3.59 Голубев I УАК2-3.60 Голубева",
            "II\n10:20-11:55": "МЕТОДЫ МАШИННОГО ОБУЧЕНИЯ лекц. УАК3-3.56 Кручинин",
            "III\n12:10-13:45": null
        }
    }
}