{
    "Четная неделя": {
        "Понедельник": {
            "I\n8:30-10:05": null,
            "II\n10:20-11:55": null,
            "III\n12:10-13:45": "РОБОТОТЕХНИЧЕСКИЕ КОМПЛЕКСЫ упр. УАК3-1.53 Мокин",
            "IV\n14:15-15:50": "МАШИНЫ НЕПР. ТРАНСПОРТА к.пр. к.3",
            "V\n16:05-17:40": null
        },
        "Вторник": {
            "I\n8:30-10:05": "ВОЕННАЯ ПОДГОТОВКА к.2",
            "II\n10:20-11:55": null,
            "III\n12:10-13:45": null,
            "IV\n14:15-15:50": null,
            "V\n16:05-17:40": null
        },
        "Среда": {
            "I\n8:30-10:05": "ЭКОНОМИКА упр. УАК1-4.67 Яловенко",
            "II\n10:20-11:55": "ЭКОНОМИКА лекц. УАК1-4.03 Яловенко",
            "III\n12:10-13:45": "ПРАВОВЕДЕНИЕ лекц. УАК3-1.60 Шафигуллина",
            "IV\n14:15-15:50": "ПРОЕКТИР.ОБЪЕКТОВ И ПРОЦЕС. НА ОСН. ЦИФР. ДВОЙНИКОВ лаб. I УАК3-1.53 Славкина",
            "V\n16:05-17:40": null
        },
        "Четверг": {
            "I\n8:30-10:05": null,
            "II\n10:20-11:55": "ПРОЕКТ. ОБЪЕКТ. И ПРОЦЕС. НА ОСН. ЦИФР. ДВОЙН. упр. УАК3-1.53 Славкина",
            "III\n12:10-13:45": "ГРУЗОПОДЪЕМНЫЕ МАШИНЫ лекц. УАК3-1.53 Славкина",
            "IV\n14:15-15:50": "ПРОЕКТИР.ОБЪЕКТОВ И ПРОЦЕС. НА ОСН. ЦИФР. ДВОЙНИКОВ лекц. УАК3-1.53 Славкина"
        },
        "Пятница": {
            "I\n8:30-10:05": null,
            "II\n10:20-11:55": null,
            "III\n12:10-13:45": "ОСНОВЫ ТЕХНОЛ. М/СТРОЕНИЯ лекц. УАК3-3.56 Федоров",
            "IV\n14:15-15:50": "ОСНОВЫ ТЕХНОЛ. М/СТРОЕНИЯ лаб. II УАК3-2.51 Федоров по расп.каф.",
            "V\n16:05-17:40": null
        },
        "Суббота": {
            "I\n8:30-10:05": "БЖД лекц. УАК3-1.60 Фатеева",
            "II\n10:20-11:55": "БЖД упр. УАК3-4.05 Фатеева",
            "III\n12:10-13:45": "ГРУЗОПОДЪЕМНЫЕ МАШИНЫ упр. УАК3-1.53 Славкина"
        }
    },
    "Нечетная неделя": {
        "Понедельник": {
            "I\n8:30-10:05": null,
            "II\n10:20-11:55": "РОБОТОТЕХНИЧЕСКИЕ КОМПЛЕКСЫ лекц. УАК3-1.53 Мокин",
            "III\n12:10-13:45": "РОБОТОТЕХНИЧЕСКИЕ КОМПЛЕКСЫ упр. УАК3-1.53 Мокин",
            "IV\n14:15-15:50": "МАШИНЫ НЕПР. ТРАНСПОРТА к.пр. к.3",
            "V\n16:05-17:40": null
        },
        "Вторник": {
            "I\n8:30-10:05": "ВОЕННАЯ ПОДГОТОВКА к.2",
            "II\n10:20-11:55": null,
            "III\n12:10-13:45": null,
            "IV\n14:15-15:50": null,
            "V\n16:05-17:40": null
        },
        "Среда": {
            "I\n8:30-10:05": "ПРОЕКТИР.ОБЪЕКТОВ И ПРОЦЕС. НА ОСН. ЦИФР. ДВОЙНИКОВ лаб. II УАК3-1.53 Славкина",
            "II\n10:20-11:55": "ЭКОНОМИКА лекц. УАК1-4.03 Яловенко",
            "III\n12:10-13:45": "ПРАВОВЕДЕНИЕ лекц. УАК3-1.60 Шафигуллина",
            "IV\n14:15-15:50": null,
            "V\n16:05-17:40": null
        },
        "Четверг": {
            "I\n8:30-10:05": null,
            "II\n10:20-11:55": "ОСНОВЫ ТЕХНОЛ. М/СТРОЕНИЯ упр. УАК3-1.29 Федоров",
            "III\n12:10-13:45": "ГРУЗОПОДЪЕМНЫЕ МАШИНЫ лекц. УАК3-1.53 Славкина",
            "IV\n14:15-15:50": "ПРОЕКТИР.ОБЪЕКТОВ И ПРОЦЕС. НА ОСН. ЦИФР. ДВОЙНИКОВ лекц. УАК3-1.53 Славкина"
        },
        "Пятница": {
            "I\n8:30-10:05": null,
            "II\n10:20-11:55": null,
            "III\n12:10-13:45": "ОСНОВЫ ТЕХНОЛ. М/СТРОЕНИЯ лекц. УАК3-3.56 Федоров",
            "IV\n14:15-15:50": "ОСНОВЫ ТЕХНОЛ. М/СТРОЕНИЯ лаб. I УАК3-2.51 Малышев по расп.каф.",
            "V\n16:05-17:40": null
        },
        "Суббота": {
            "I\n8:30-10:05": "БЖД лекц. УАК3-1.60 Фатеева",
            "II\n10:20-11:55": "БЖД лаб. УАК3-4.05 Фатеева",
            "III\n12:10-13:45": "ГРУЗОПОДЪЕМНЫЕ МАШИНЫ упр. УАК3-1.53 Славкина"
        }
    }
}